treelang/__init__.py
treelang/ai/arborist.py
treelang/ai/memory.py
treelang/ai/prompt.py
treelang/ai/provider.py
treelang/ai/selector.py
treelang/trees/schemas/__init__.py
treelang/trees/schemas/v1.py
treelang/trees/tree.py
treelang-0.9.0.dist-info/METADATA
treelang-0.9.0.dist-info/WHEEL
treelang-0.9.0.dist-info/licenses/LICENSE
treelang-0.9.0.dist-info/RECORD
