Metadata-Version: 2.4
Name: treelang
Version: 0.9.0
Summary: LLM function calling on steroids using Abstract Syntax Trees.
License: MIT
License-File: LICENSE
Author: csolar
Author-email: cristiano.solarino@brightminded.com
Requires-Python: >=3.12
Classifier: License :: OSI Approved :: MIT License
Classifier: Programming Language :: Python :: 3
Classifier: Programming Language :: Python :: 3.12
Classifier: Programming Language :: Python :: 3.13
Classifier: Programming Language :: Python :: 3.14
Requires-Dist: dotenv (>=0.9.9,<0.10.0)
Requires-Dist: mcp (>=1.23.0,<2.0.0)
Requires-Dist: openai (>=1.68.2,<2.0.0)
Project-URL: Homepage, https://github.com/cs0lar/treelang
Project-URL: Issues, https://github.com/cs0lar/treelang/issues
